<kanji midashi="備" id="5099">
<strokegr element="備">
	<strokegr element="亻" variant="true" original="人" position="left" radical="general">
		<stroke type="㇒"/>
		<stroke type="㇑"/>
	</strokegr>
	<strokegr position="right" phon="備right">
		<strokegr element="艹" variant="true" original="艸">
			<stroke type="㇐"/>
			<stroke type="㇑a"/>
			<stroke type="㇑a"/>
		</strokegr>
		<strokegr element="厂">
			<stroke type="㇐"/>
			<stroke type="㇒"/>
		</strokegr>
		<strokegr element="用">
			<stroke type="㇑/㇒"/>
			<stroke type="㇆a"/>
			<stroke type="㇐a"/>
			<stroke type="㇐a"/>
			<stroke type="㇑"/>
		</strokegr>
	</strokegr>
</strokegr>
</kanji>
