<kanji midashi="協" id="5354">
<strokegr element="協">
	<strokegr element="十" position="left" radical="general">
		<stroke type="㇐"/>
		<stroke type="㇑"/>
	</strokegr>
	<strokegr position="right" phon="劦">
		<strokegr element="力" position="top">
			<stroke type="㇆"/>
			<stroke type="㇒"/>
		</strokegr>
		<strokegr position="bottom">
			<strokegr element="力">
				<stroke type="㇆"/>
				<stroke type="㇒"/>
			</strokegr>
			<strokegr element="力">
				<stroke type="㇆"/>
				<stroke type="㇒"/>
			</strokegr>
		</strokegr>
	</strokegr>
</strokegr>
</kanji>
