<kanji midashi="嫁" id="5ac1Kaisho">
<strokegr element="嫁">
	<strokegr element="女" variant="true" position="left" radical="general">
		<stroke type="㇛"/>
		<stroke type="㇒"/>
		<stroke type="㇀/㇐"/>
	</strokegr>
	<strokegr element="家" position="right">
		<strokegr element="宀" position="top">
			<stroke type="㇔/㇑a"/>
			<stroke type="㇔"/>
			<stroke type="㇖"/>
		</strokegr>
		<strokegr element="豕" position="bottom">
			<stroke type="㇐"/>
			<stroke type="㇒"/>
			<stroke type="㇕v"/>
			<stroke type="㇒"/>
			<stroke type="㇒"/>
			<stroke type="㇒"/>
			<stroke type="㇏"/>
		</strokegr>
	</strokegr>
</strokegr>
</kanji>
