<kanji midashi="嫐" id="5ad0">
<strokegr element="嫐">
	<strokegr element="娚" position="left">
		<strokegr element="女" position="left" radical="tradit">
			<stroke type="㇛"/>
			<stroke type="㇒"/>
			<stroke type="㇐"/>
		</strokegr>
		<strokegr element="男" position="right">
			<strokegr element="田" position="top">
				<stroke type="㇑"/>
				<stroke type="㇕a"/>
				<stroke type="㇑a"/>
				<stroke type="㇐a"/>
				<stroke type="㇐a"/>
			</strokegr>
			<strokegr element="力" position="bottom">
				<stroke type="㇆"/>
				<stroke type="㇒"/>
			</strokegr>
		</strokegr>
	</strokegr>
	<strokegr element="女" position="right" radical="tradit">
		<stroke type="㇛"/>
		<stroke type="㇒"/>
		<stroke type="㇐"/>
	</strokegr>
</strokegr>
</kanji>
