<kanji midashi="室" id="5ba4KaishoVtFst">
<strokegr element="室">
	<strokegr element="宀" position="top" radical="general">
		<stroke type="㇑a"/>
		<strokegr element="冖">
			<stroke type="㇔"/>
			<stroke type="㇖b"/>
		</strokegr>
	</strokegr>
	<strokegr element="至" position="bottom">
		<stroke type="㇐"/>
		<stroke type="㇜"/>
		<stroke type="㇔"/>
		<strokegr element="土" variant="true">
			<stroke type="㇑a"/>
			<stroke type="㇐"/>
			<stroke type="㇐"/>
		</strokegr>
	</strokegr>
</strokegr>
</kanji>
