<kanji midashi="昇" id="6607Kaisho">
<strokegr element="昇">
	<strokegr element="日" position="top" radical="general">
		<stroke type="㇑"/>
		<stroke type="㇕a"/>
		<stroke type="㇐a"/>
		<stroke type="㇐a"/>
	</strokegr>
	<strokegr element="升" position="bottom">
		<strokegr element="丿">
			<stroke type="㇒"/>
		</strokegr>
		<strokegr element="廾" variant="true">
			<strokegr element="丿">
				<stroke type="㇒"/>
			</strokegr>
			<strokegr element="十">
				<stroke type="㇐"/>
				<stroke type="㇑"/>
			</strokegr>
		</strokegr>
	</strokegr>
</strokegr>
</kanji>
