<kanji midashi="梢" id="68a2Kaisho">
<strokegr element="梢">
	<strokegr element="木" position="left" radical="general">
		<stroke type="㇐"/>
		<stroke type="㇑"/>
		<stroke type="㇒"/>
		<stroke type="㇔/㇏"/>
	</strokegr>
	<strokegr element="肖" position="right">
		<strokegr element="⺌" variant="true" original="小" position="top">
			<stroke type="㇑a"/>
			<stroke type="㇔"/>
			<stroke type="㇒"/>
		</strokegr>
		<strokegr element="月" position="bottom">
			<stroke type="㇑/㇒"/>
			<stroke type="㇆a"/>
			<stroke type="㇐a"/>
			<stroke type="㇐a"/>
		</strokegr>
	</strokegr>
</strokegr>
</kanji>
