<kanji midashi="洪" id="6d2a">
<strokegr element="洪">
	<strokegr element="氵" variant="true" original="水" position="left" radical="general">
		<stroke type="㇔"/>
		<stroke type="㇔"/>
		<stroke type="㇀"/>
	</strokegr>
	<strokegr element="共" position="right" phon="共">
		<strokegr position="top">
			<stroke type="㇐"/>
			<stroke type="㇑a"/>
			<stroke type="㇑a"/>
			<stroke type="㇐"/>
		</strokegr>
		<strokegr element="八" position="bottom">
			<stroke type="㇒"/>
			<stroke type="㇔"/>
		</strokegr>
	</strokegr>
</strokegr>
</kanji>
