<kanji midashi="洲" id="6d32">
<strokegr element="洲">
	<strokegr element="氵" variant="true" original="水" position="left" radical="general">
		<stroke type="㇔"/>
		<stroke type="㇔"/>
		<stroke type="㇀"/>
	</strokegr>
	<strokegr element="州" position="right">
		<strokegr element="丶">
			<stroke type="㇔"/>
		</strokegr>
		<strokegr element="川" part="1" variant="true" original="巛">
			<stroke type="㇒"/>
		</strokegr>
		<strokegr element="丶">
			<stroke type="㇔"/>
		</strokegr>
		<strokegr element="川" part="2" variant="true" original="巛">
			<stroke type="㇑"/>
		</strokegr>
		<strokegr element="丶">
			<stroke type="㇔"/>
		</strokegr>
		<strokegr element="川" variant="true" original="巛">
			<stroke type="㇑"/>
		</strokegr>
	</strokegr>
</strokegr>
</kanji>
