<kanji midashi="物" id="7269">
<strokegr element="物">
	<strokegr element="牛" variant="true" position="left" radical="general">
		<stroke type="㇒"/>
		<stroke type="㇐"/>
		<stroke type="㇑"/>
		<stroke type="㇀"/>
	</strokegr>
	<strokegr element="勿" position="right" phon="勿">
		<strokegr element="勹">
			<strokegr element="丿">
				<stroke type="㇒"/>
			</strokegr>
			<stroke type="㇆"/>
		</strokegr>
		<strokegr element="丿">
			<stroke type="㇒"/>
		</strokegr>
		<strokegr element="丿">
			<stroke type="㇒"/>
		</strokegr>
	</strokegr>
</strokegr>
</kanji>
