<kanji midashi="珱" id="73f1">
<strokegr element="珱">
	<strokegr element="王" original="玉" partial="true" position="left" radical="tradit">
		<stroke type="㇐"/>
		<stroke type="㇑a"/>
		<stroke type="㇐"/>
		<stroke type="㇐"/>
	</strokegr>
	<strokegr position="right">
		<strokegr element="⺍" original="つ" position="top">
			<stroke type="㇔"/>
			<stroke type="㇔"/>
			<stroke type="㇒"/>
		</strokegr>
		<strokegr element="女" position="bottom">
			<stroke type="㇛"/>
			<stroke type="㇒"/>
			<stroke type="㇐"/>
		</strokegr>
	</strokegr>
</strokegr>
</kanji>
