<kanji midashi="瘴" id="7634Kaisho">
<strokegr element="瘴">
	<strokegr element="疒" position="tare" radical="general">
		<stroke type="㇑a"/>
		<stroke type="㇐"/>
		<stroke type="㇒"/>
		<stroke type="㇔"/>
		<stroke type="㇀"/>
	</strokegr>
	<strokegr element="章">
		<strokegr element="立" position="top">
			<strokegr element="亠" position="top">
				<stroke type="㇑a"/>
				<stroke type="㇐"/>
			</strokegr>
			<strokegr position="bottom">
				<stroke type="㇔"/>
				<stroke type="㇒"/>
				<stroke type="㇐"/>
			</strokegr>
		</strokegr>
		<strokegr element="早" position="bottom">
			<strokegr element="日">
				<stroke type="㇑"/>
				<stroke type="㇕a"/>
				<stroke type="㇐a"/>
				<stroke type="㇐a"/>
			</strokegr>
			<strokegr element="十">
				<stroke type="㇐"/>
				<stroke type="㇑"/>
			</strokegr>
		</strokegr>
	</strokegr>
</strokegr>
</kanji>
