<kanji midashi="紋" id="7d0b">
<strokegr element="紋">
	<strokegr element="糸" position="left" radical="general">
		<stroke type="㇜"/>
		<stroke type="㇜"/>
		<stroke type="㇔"/>
		<stroke type="㇑"/>
		<stroke type="㇒"/>
		<stroke type="㇔"/>
	</strokegr>
	<strokegr element="文" position="right" phon="文">
		<strokegr element="亠" position="top">
			<stroke type="㇑a"/>
			<stroke type="㇐"/>
		</strokegr>
		<strokegr element="乂" position="bottom">
			<stroke type="㇒"/>
			<stroke type="㇏"/>
		</strokegr>
	</strokegr>
</strokegr>
</kanji>
