<kanji midashi="紮" id="7d2e">
<strokegr element="紮">
	<strokegr element="札" position="top">
		<strokegr element="木" position="left">
			<stroke type="㇐"/>
			<stroke type="㇑"/>
			<stroke type="㇒"/>
			<stroke type="㇏"/>
		</strokegr>
		<strokegr element="乙" variant="true" position="right">
			<stroke type="㇟"/>
		</strokegr>
	</strokegr>
	<strokegr element="糸" position="bottom" radical="general">
		<stroke type="㇜"/>
		<stroke type="㇜"/>
		<stroke type="㇔"/>
		<stroke type="㇑"/>
		<stroke type="㇒"/>
		<stroke type="㇔"/>
	</strokegr>
</strokegr>
</kanji>
