<kanji midashi="絡" id="7d61">
<strokegr element="絡">
	<strokegr element="糸" position="left" radical="general">
		<stroke type="㇜"/>
		<stroke type="㇜"/>
		<stroke type="㇔"/>
		<stroke type="㇑"/>
		<stroke type="㇒"/>
		<stroke type="㇔"/>
	</strokegr>
	<strokegr element="各" position="right" phon="各">
		<strokegr element="夂" position="top">
			<stroke type="㇒"/>
			<stroke type="㇇"/>
			<stroke type="㇏"/>
		</strokegr>
		<strokegr element="口" position="bottom">
			<stroke type="㇑"/>
			<stroke type="㇕b"/>
			<stroke type="㇐b"/>
		</strokegr>
	</strokegr>
</strokegr>
</kanji>
