<kanji midashi="膂" id="8182Kaisho">
<strokegr element="膂">
	<strokegr element="旅" position="top">
		<strokegr element="方" position="left">
			<strokegr element="亠" position="top">
				<stroke type="㇑a"/>
				<stroke type="㇐"/>
			</strokegr>
			<strokegr position="bottom">
				<stroke type="㇆a"/>
				<stroke type="㇒"/>
			</strokegr>
		</strokegr>
		<strokegr position="right">
			<stroke type="㇒"/>
			<stroke type="㇐"/>
			<strokegr element="亻" variant="true" original="人">
				<stroke type="㇒"/>
				<stroke type="㇑"/>
			</strokegr>
			<stroke type="㇒"/>
			<stroke type="㇏"/>
		</strokegr>
	</strokegr>
	<strokegr element="月" variant="true" original="肉" position="bottom" radical="general">
		<stroke type="㇒"/>
		<stroke type="㇆a"/>
		<stroke type="㇐a"/>
		<stroke type="㇐a"/>
	</strokegr>
</strokegr>
</kanji>
