<kanji midashi="葢" id="8462">
<strokegr element="葢">
	<strokegr element="艹" variant="true" original="艸" position="top" radical="general">
		<stroke type="㇐"/>
		<stroke type="㇑a"/>
		<stroke type="㇑a"/>
	</strokegr>
	<strokegr position="bottom">
		<strokegr element="太" position="top">
			<strokegr element="大" position="top">
				<stroke type="㇐"/>
				<stroke type="㇒"/>
				<stroke type="㇏"/>
			</strokegr>
			<strokegr element="丶" position="bottom">
				<stroke type="㇔"/>
			</strokegr>
		</strokegr>
		<strokegr element="皿" position="bottom">
			<stroke type="㇑a"/>
			<stroke type="㇕b"/>
			<stroke type="㇑a"/>
			<stroke type="㇑a"/>
			<stroke type="㇐"/>
		</strokegr>
	</strokegr>
</strokegr>
</kanji>
