<kanji midashi="袵" id="88b5">
<strokegr element="袵">
	<strokegr element="衤" variant="true" original="衣" position="left" radical="general">
		<stroke type="㇔"/>
		<stroke type="㇇"/>
		<stroke type="㇑"/>
		<stroke type="㇒"/>
		<stroke type="㇔"/>
	</strokegr>
	<strokegr element="任" position="right">
		<strokegr element="亻" variant="true" original="人" position="left">
			<stroke type="㇒"/>
			<stroke type="㇑"/>
		</strokegr>
		<strokegr element="壬" position="right">
			<strokegr element="丿">
				<stroke type="㇒"/>
			</strokegr>
			<strokegr element="士">
				<stroke type="㇐"/>
				<stroke type="㇑a"/>
				<stroke type="㇐"/>
			</strokegr>
		</strokegr>
	</strokegr>
</strokegr>
</kanji>
