<kanji midashi="陬" id="966c">
<strokegr element="陬">
	<strokegr element="⻖" variant="true" original="阜" position="left" radical="general">
		<stroke type="㇇"/>
		<stroke type="㇕va"/>
		<stroke type="㇑"/>
	</strokegr>
	<strokegr element="取" position="right">
		<strokegr element="耳" position="left">
			<stroke type="㇐"/>
			<stroke type="㇑a"/>
			<stroke type="㇐a"/>
			<stroke type="㇐a"/>
			<stroke type="㇀"/>
			<stroke type="㇑"/>
		</strokegr>
		<strokegr element="又" position="right">
			<stroke type="㇇"/>
			<stroke type="㇏"/>
		</strokegr>
	</strokegr>
</strokegr>
</kanji>
