<kanji midashi="駈" id="99c8">
<strokegr element="駈">
	<strokegr element="馬" position="left" radical="general">
		<stroke type="㇑"/>
		<stroke type="㇐b"/>
		<stroke type="㇑a"/>
		<stroke type="㇐b"/>
		<stroke type="㇐b"/>
		<stroke type="㇆a"/>
		<strokegr element="灬" variant="true" original="火">
			<stroke type="㇔"/>
			<stroke type="㇔"/>
			<stroke type="㇔"/>
			<stroke type="㇔"/>
		</strokegr>
	</strokegr>
	<strokegr element="丘" position="right">
		<strokegr element="斤">
			<stroke type="㇒"/>
			<stroke type="㇑"/>
			<stroke type="㇐"/>
			<stroke type="㇑"/>
		</strokegr>
		<strokegr element="一">
			<stroke type="㇐"/>
		</strokegr>
	</strokegr>
</strokegr>
</kanji>
