<kanji midashi="鰹" id="9c39Kaisho">
<strokegr element="鰹">
	<strokegr element="魚" position="left" radical="general">
		<strokegr element="𠂊" variant="true" original="勹" position="top">
			<stroke type="㇒"/>
			<stroke type="㇇"/>
		</strokegr>
		<strokegr position="bottom">
			<strokegr element="田">
				<stroke type="㇑"/>
				<stroke type="㇕a"/>
				<stroke type="㇑a"/>
				<stroke type="㇐a"/>
				<stroke type="㇐a"/>
			</strokegr>
			<strokegr element="灬" variant="true" original="火">
				<stroke type="㇔"/>
				<stroke type="㇔"/>
				<stroke type="㇔"/>
				<stroke type="㇔"/>
			</strokegr>
		</strokegr>
	</strokegr>
	<strokegr element="堅" position="right">
		<strokegr position="top">
			<strokegr element="臣" position="left">
				<stroke type="㇑"/>
				<stroke type="㇐b"/>
				<stroke type="㇑a"/>
				<stroke type="㇕b"/>
				<stroke type="㇐b"/>
				<stroke type="㇑a"/>
				<stroke type="㇐b"/>
			</strokegr>
			<strokegr element="又" position="right">
				<stroke type="㇇"/>
				<stroke type="㇏"/>
			</strokegr>
		</strokegr>
		<strokegr element="土" position="bottom">
			<stroke type="㇐"/>
			<stroke type="㇑a"/>
			<stroke type="㇐"/>
		</strokegr>
	</strokegr>
</strokegr>
</kanji>
