<kanji midashi="黶" id="9ef6KaishoVtLst">
<strokegr element="黶">
	<strokegr element="厭" position="top">
		<strokegr element="厂" position="tare">
			<stroke type="㇐"/>
			<stroke type="㇒"/>
		</strokegr>
		<strokegr position="left">
			<strokegr element="日" position="top">
				<stroke type="㇑"/>
				<stroke type="㇕a"/>
				<stroke type="㇐a"/>
				<stroke type="㇐a"/>
			</strokegr>
			<strokegr element="月" position="bottom">
				<stroke type="㇒"/>
				<stroke type="㇆a"/>
				<stroke type="㇐a"/>
				<stroke type="㇐a"/>
			</strokegr>
		</strokegr>
		<strokegr element="犬" position="right">
			<strokegr element="大">
				<stroke type="㇐"/>
				<stroke type="㇒"/>
				<stroke type="㇏"/>
			</strokegr>
			<strokegr element="丶">
				<stroke type="㇔"/>
			</strokegr>
		</strokegr>
	</strokegr>
	<strokegr element="黑" variant="true" original="黒" position="bottom" radical="tradit">
		<strokegr element="里" variant="true" position="top">
			<stroke type="㇑"/>
			<stroke type="㇕"/>
			<stroke type="㇔"/>
			<stroke type="㇒"/>
			<stroke type="㇐"/>
			<stroke type="㇐"/>
			<stroke type="㇐"/>
			<stroke type="㇑"/>
		</strokegr>
		<strokegr element="灬" variant="true" original="火" position="bottom">
			<stroke type="㇔"/>
			<stroke type="㇔"/>
			<stroke type="㇔"/>
			<stroke type="㇔"/>
		</strokegr>
	</strokegr>
</strokegr>
</kanji>
